aligi.py
aligi-1.1.0.dist-info/LICENSE
aligi-1.1.0.dist-info/METADATA
aligi-1.1.0.dist-info/WHEEL
aligi-1.1.0.dist-info/top_level.txt
aligi-1.1.0.dist-info/RECORD
